mmlspark/__init__.py
mmlspark/recommendation/RankingTrainValidationSplit.py
mmlspark/recommendation/RankingTrainValidationSplitModel.py
mmlspark/recommendation/SAR.py
mmlspark/recommendation/SARModel.py
mmlspark/recommendation/__init__.py
pyspark/jars/mmlspark_2.11-0.18.1.jar
dciborowMMLSpark-0.0.29.dist-info/LICENSE.txt
dciborowMMLSpark-0.0.29.dist-info/METADATA
dciborowMMLSpark-0.0.29.dist-info/WHEEL
dciborowMMLSpark-0.0.29.dist-info/top_level.txt
dciborowMMLSpark-0.0.29.dist-info/zip-safe
dciborowMMLSpark-0.0.29.dist-info/RECORD
