Metadata-Version: 2.1
Name: dciborowMMLSpark
Version: 0.0.29
Summary: Microsoft ML for Spark
Home-page: https://github.com/dciborow/mmlspark
Author: Microsoft
Author-email: mmlspark-support@microsoft.com
License: MIT
Platform: UNKNOWN
Classifier: Development Status :: 3 - Alpha
Classifier: Intended Audience :: Developers
Classifier: License :: OSI Approved :: MIT License
Classifier: Programming Language :: Python :: 3
Requires-Dist: pyspark
Requires-Dist: numpy
